MANIFEST.in
README.md
setup.py
lsalib/__init__.py
lsalib.egg-info/PKG-INFO
lsalib.egg-info/SOURCES.txt
lsalib.egg-info/dependency_links.txt
lsalib.egg-info/not-zip-safe
lsalib.egg-info/requires.txt
lsalib.egg-info/top_level.txt