Metadata-Version: 1.0
Name: lsalib
Version: 0.10.2
Summary: Basic Latent Semantic Analysis library
Home-page: https://github.com/CrakeNotSnowman/LatentSemanticAnalysis/lsalib
Author: Keith Murray
Author-email: kmurrayis@gmail.com
License: MIT
Platform: UNKNOWN
